desmume/__init__.py
desmume/controls.py
desmume/emulator.py
desmume/i18n_util.py
desmume/libdesmume.so
desmume/frontend/PyDeSmuMe.glade
desmume/frontend/__init__.py
desmume/frontend/controller.py
desmume/frontend/gtk_drawing_area_desmume.py
desmume/frontend/main.py
desmume/frontend/widget_to_primitive.py
desmume/frontend/control_ui/PyDeSmuMe_controls.glade
desmume/frontend/control_ui/__init__.py
desmume/frontend/control_ui/joystick_controls.py
desmume/frontend/control_ui/keyboard_controls.py
desmume/frontend/gtk_drawing_impl/__init__.py
desmume/frontend/gtk_drawing_impl/opengl.py
desmume/frontend/gtk_drawing_impl/software.py
py_desmume.libs/libSDL2-2-395aae34.0.so.0.22.0
py_desmume.libs/libSoundTouch-3ae0d3ef.so.2.0.0
py_desmume.libs/libibverbs-1de1263b.so.1.14.48.0
py_desmume.libs/libnl-3-47cd035c.so.200.26.0
py_desmume.libs/libnl-route-3-3ad497a3.so.200.26.0
py_desmume.libs/libpcap-2b6f73a4.so.1.9.1
py_desmume-0.0.9.dist-info/METADATA
py_desmume-0.0.9.dist-info/WHEEL
py_desmume-0.0.9.dist-info/top_level.txt
py_desmume-0.0.9.dist-info/RECORD
py_desmume-0.0.9.dist-info/licenses/LICENSE
py_desmume-0.0.9.dist-info/sboms/auditwheel.cdx.json
