Metadata-Version: 2.1
Name: py-desmume
Version: 0.0.9
Summary: Python library to interface with DeSmuME, the Nintendo DS emulator + sample GTK-based frontend
Home-page: https://github.com/SkyTemple/py-desmume/
Classifier: Development Status :: 3 - Alpha
Classifier: Programming Language :: Python
Classifier: License :: OSI Approved :: GNU General Public License v3 or later (GPLv3+)
Classifier: Programming Language :: Python :: 3.7
Classifier: Programming Language :: Python :: 3.8
Classifier: Programming Language :: Python :: 3.9
Classifier: Programming Language :: Python :: 3.10
Classifier: Programming Language :: Python :: 3.11
Classifier: Programming Language :: Python :: 3.12
Classifier: Programming Language :: Python :: 3.13
Requires-Python: >=3.7
License-File: LICENSE
Requires-Dist: Pillow >=6.1.0
